setup.py
dfract/__init__.py
dfract/accessors.py
dfract/aggregate.py
dfract/autoimp.py
dfract/autoimp2.py
dfract/builder.py
dfract/cache_utils.py
dfract/client.py
dfract/config.py
dfract/dataset.py
dfract/datastream.py
dfract/docker_utils.py
dfract/events.py
dfract/index.py
dfract/jobqueue.py
dfract/linked_data.py
dfract/log.py
dfract/object.py
dfract/persistency.py
dfract/querylanguage.py
dfract/serialization.py
dfract/server.py
dfract/specification.py
dfract/tornado_gateway.py
dfract/utils.py
dfract.egg-info/PKG-INFO
dfract.egg-info/SOURCES.txt
dfract.egg-info/dependency_links.txt
dfract.egg-info/entry_points.txt
dfract.egg-info/requires.txt
dfract.egg-info/top_level.txt
dfract/datasets/__init__.py
dfract/datasets/cache.py
dfract/datasets/cartesian.py
dfract/datasets/dfracthelper.py
dfract/datasets/download.py
dfract/datasets/dslice.py
dfract/datasets/git.py
dfract/datasets/proxy.py
dfract/datasets/pytransform.py
dfract/datasets/shuffled.py
dfract/datastreams/__init__.py
dfract/datastreams/dfracthelper.py
dfract/datastreams/dslice.py
dfract/datastreams/git.py
dfract/datastreams/mux.py
dfract/datastreams/proxy.py
dfract/datastreams/pytransform.py
dfract/datastreams/ratelimit.py
dfract/datastreams/upcheck.py