Metadata-Version: 1.1
Name: dfract
Version: 0.1.2
Summary: DFRACT  -
Home-page: https://gitlab.pet.wide.io/wide-io/dfract.git
Author: WIDE IO LTD
Author-email: support@wide.io
License: BSD
Platform: UNKNOWN
Classifier: Development Status :: 3 - Alpha
Classifier: Intended Audience :: Developers
Classifier: Natural Language :: English
Classifier: License :: OSI Approved :: MIT License
Classifier: Programming Language :: Python
Classifier: Programming Language :: Python :: 2.7
Classifier: Programming Language :: Python :: 3.5
Classifier: Programming Language :: Python :: Implementation :: CPython
